RTOC/LoggerPlugin.py
RTOC/RTOC.py
RTOC/Template.py
RTOC/__init__.py
RTOC/__main__.py
RTOC/index.html
RTOC/jsonsocket.py
RTOC/requirenments.txt
RTOC/.vscode/settings.json
RTOC/RTLogger/Console.py
RTOC/RTLogger/Daemon.py
RTOC/RTLogger/DeviceFunctions.py
RTOC/RTLogger/EventActionFunctions.py
RTOC/RTLogger/NetworkFunctions.py
RTOC/RTLogger/RTLogger.py
RTOC/RTLogger/RTOC_Web.py
RTOC/RTLogger/RTOC_Web_standalone.py
RTOC/RTLogger/RTRemote.py
RTOC/RTLogger/RTWebsocket.py
RTOC/RTLogger/RTWebsocketClient.py
RTOC/RTLogger/RTWebsocketServer.py
RTOC/RTLogger/RT_data.py
RTOC/RTLogger/ScriptFunctions.py
RTOC/RTLogger/__init__.py
RTOC/RTLogger/__main__.py
RTOC/RTLogger/importCode.py
RTOC/RTLogger/jsonsocket.py
RTOC/RTLogger/loggerlib.py
RTOC/RTLogger/requirenments.txt
RTOC/RTLogger/scriptLibrary.py
RTOC/RTLogger/telegramBot.py
RTOC/RTLogger/websocket_server.py
RTOC/RTLogger/__pycache__/Console.cpython-36.pyc
RTOC/RTLogger/__pycache__/Daemon.cpython-36.pyc
RTOC/RTLogger/__pycache__/DeviceFunctions.cpython-36.pyc
RTOC/RTLogger/__pycache__/EventActionFunctions.cpython-36.pyc
RTOC/RTLogger/__pycache__/LoggerPlugin.cpython-36.pyc
RTOC/RTLogger/__pycache__/NetworkFunctions.cpython-36.pyc
RTOC/RTLogger/__pycache__/RTLogger.cpython-36.pyc
RTOC/RTLogger/__pycache__/RTOC_Web.cpython-36.pyc
RTOC/RTLogger/__pycache__/RTOC_Web_standalone.cpython-36.pyc
RTOC/RTLogger/__pycache__/RTRemote.cpython-36.pyc
RTOC/RTLogger/__pycache__/RTRemote_Websocket.cpython-36.pyc
RTOC/RTLogger/__pycache__/RTWebsocket.cpython-36.pyc
RTOC/RTLogger/__pycache__/RTWebsocketClient.cpython-36.pyc
RTOC/RTLogger/__pycache__/RTWebsocketServer.cpython-36.pyc
RTOC/RTLogger/__pycache__/RT_data.cpython-36.pyc
RTOC/RTLogger/__pycache__/RT_database.cpython-36.pyc
RTOC/RTLogger/__pycache__/RT_datalocal.cpython-36.pyc
RTOC/RTLogger/__pycache__/ScriptFunctions.cpython-36.pyc
RTOC/RTLogger/__pycache__/__init__.cpython-36.pyc
RTOC/RTLogger/__pycache__/__main__.cpython-36.pyc
RTOC/RTLogger/__pycache__/importCode.cpython-36.pyc
RTOC-3.0.dist-info/LICENSE
RTOC-3.0.dist-info/METADATA
RTOC-3.0.dist-info/WHEEL
RTOC-3.0.dist-info/entry_points.txt
RTOC-3.0.dist-info/top_level.txt
RTOC-3.0.dist-info/RECORD
