Metadata-Version: 2.1
Name: RTOC
Version: 3.0
Summary: RealTime OpenControl
Home-page: https://github.com/Haschtl/RealTimeOpenControl
Author: Sebastian Keller
Author-email: sebastiankeller@online.de
License: GNU
Platform: UNKNOWN
Classifier: Programming Language :: Python :: 3
Classifier: Environment :: Other Environment
Classifier: Intended Audience :: Science/Research
Classifier: License :: OSI Approved :: GNU Lesser General Public License v3 (LGPLv3)
Classifier: Operating System :: OS Independent
Classifier: Topic :: Scientific/Engineering :: Visualization
Classifier: Topic :: Software Development :: User Interfaces
Requires-Python: >=3
Requires-Dist: numpy
Requires-Dist: requests
Requires-Dist: python-nmap
Requires-Dist: whaaaaat
Requires-Dist: prompt-toolkit
Requires-Dist: pycryptodomex
Requires-Dist: websocket-client
Provides-Extra: all
Requires-Dist: pyqt5 ; extra == 'all'
Requires-Dist: pyqtgraph ; extra == 'all'
Requires-Dist: markdown2 ; extra == 'all'
Requires-Dist: pyGithub ; extra == 'all'
Requires-Dist: pandas ; extra == 'all'
Requires-Dist: scipy ; extra == 'all'
Requires-Dist: ezodf ; extra == 'all'
Requires-Dist: xlsxwriter ; extra == 'all'
Requires-Dist: matplotlib ; extra == 'all'
Requires-Dist: python-telegram-bot ; extra == 'all'
Requires-Dist: dash-table ; extra == 'all'
Requires-Dist: statsmodels ; extra == 'all'
Requires-Dist: scikit-learn ; extra == 'all'
Requires-Dist: scikit-metrics ; extra == 'all'
Requires-Dist: patsy ; extra == 'all'
Requires-Dist: psycopg2 ; extra == 'all'
Provides-Extra: gui
Requires-Dist: pyqt5 ; extra == 'gui'
Requires-Dist: pyqtgraph ; extra == 'gui'
Requires-Dist: markdown2 ; extra == 'gui'
Requires-Dist: pyGithub ; extra == 'gui'
Requires-Dist: pandas ; extra == 'gui'
Requires-Dist: scipy ; extra == 'gui'
Requires-Dist: ezodf ; extra == 'gui'
Requires-Dist: xlsxwriter ; extra == 'gui'
Provides-Extra: telegram
Requires-Dist: matplotlib ; extra == 'telegram'
Requires-Dist: python-telegram-bot ; extra == 'telegram'
